a3/__init__.py
a3/cli.py
a3/config.py
a3/clients/__init__.py
a3/clients/base.py
a3/clients/openrouter.py
a3/core/__init__.py
a3/core/api.py
a3/core/code_syntax_fixer.py
a3/core/dependency_driven_planner.py
a3/core/error_handling.py
a3/core/gap_analyzer.py
a3/core/import_issue_detector.py
a3/core/interfaces.py
a3/core/migration.py
a3/core/models.py
a3/core/requirement_driven_function_generator.py
a3/core/requirement_parser.py
a3/core/structured_document_generator.py
a3/core/user_feedback.py
a3/core/validation.py
a3/engines/__init__.py
a3/engines/base.py
a3/engines/code_executor.py
a3/engines/code_generator.py
a3/engines/database_analyzer.py
a3/engines/debug_analyzer.py
a3/engines/integration.py
a3/engines/planning.py
a3/engines/project_analyzer.py
a3/engines/specification.py
a3/engines/test_generator.py
a3/managers/__init__.py
a3/managers/base.py
a3/managers/data_source_manager.py
a3/managers/dependency.py
a3/managers/filesystem.py
a3/managers/package_manager.py
a3/managers/project.py
a3/managers/state.py
a3-0.4.14.dist-info/licenses/LICENSE
a3-0.4.14.dist-info/METADATA
a3-0.4.14.dist-info/WHEEL
a3-0.4.14.dist-info/entry_points.txt
a3-0.4.14.dist-info/top_level.txt
a3-0.4.14.dist-info/RECORD
