Metadata-Version: 2.4
Name: a3
Version: 0.4.14
Summary: AI-powered project builder that automates modular coding project creation
Author-email: "Technical Ping, LLC" <contact@technical-ping.com>
License: MIT
Project-URL: Homepage, https://github.com/Nickm1128/A3
Project-URL: Repository, https://github.com/Nickm1128/A3
Project-URL: Issues, https://github.com/Nickm1128/A3/issues
Classifier: Development Status :: 3 - Alpha
Classifier: Intended Audience :: Developers
Classifier: License :: OSI Approved :: MIT License
Classifier: Programming Language :: Python :: 3
Classifier: Programming Language :: Python :: 3.8
Classifier: Programming Language :: Python :: 3.9
Classifier: Programming Language :: Python :: 3.10
Classifier: Programming Language :: Python :: 3.11
Requires-Python: >=3.8
License-File: LICENSE
Requires-Dist: openai>=1.0.0
Requires-Dist: requests>=2.28.0
Requires-Dist: typing-extensions>=4.0.0
Requires-Dist: docstring-parser>=0.15
Requires-Dist: coverage>=7.0.0
Requires-Dist: pytest>=7.0.0
Requires-Dist: psycopg2-binary>=2.9.0
Provides-Extra: dev
Requires-Dist: pytest-cov>=4.0.0; extra == "dev"
Requires-Dist: mypy>=1.0.0; extra == "dev"
Requires-Dist: black>=22.0.0; extra == "dev"
Requires-Dist: flake8>=5.0.0; extra == "dev"
Dynamic: license-file
